styletts2_fork/__init__.py
styletts2_fork/Configs/config.yml
styletts2_fork/Configs/config_ft.yml
styletts2_fork/Configs/config_libritts.yml
styletts2_fork/LICENSE
styletts2_fork/losses.py
styletts2_fork/meldataset.py
styletts2_fork/models.py
styletts2_fork/Modules/__init__.py
styletts2_fork/Modules/diffusion/__init__.py
styletts2_fork/Modules/diffusion/diffusion.py
styletts2_fork/Modules/diffusion/modules.py
styletts2_fork/Modules/diffusion/sampler.py
styletts2_fork/Modules/diffusion/utils.py
styletts2_fork/Modules/discriminators.py
styletts2_fork/Modules/hifigan.py
styletts2_fork/Modules/istftnet.py
styletts2_fork/Modules/slmadv.py
styletts2_fork/Modules/utils.py
styletts2_fork/optimizers.py
styletts2_fork/phoneme.py
styletts2_fork/requirements.txt
styletts2_fork/text_utils.py
styletts2_fork/tts.py
styletts2_fork/Utils/__init__.py
styletts2_fork/Utils/ASR/__init__.py
styletts2_fork/Utils/ASR/config.yml
styletts2_fork/Utils/ASR/layers.py
styletts2_fork/Utils/ASR/models.py
styletts2_fork/Utils/JDC/__init__.py
styletts2_fork/Utils/JDC/model.py
styletts2_fork/Utils/PLBERT/config.yml
styletts2_fork/Utils/PLBERT/util.py
styletts2_fork/utils.py
styletts2_fork-0.0.3.dist-info/LICENSE
styletts2_fork-0.0.3.dist-info/METADATA
styletts2_fork-0.0.3.dist-info/WHEEL
styletts2_fork-0.0.3.dist-info/RECORD
